simple_calculator_test/__init__.py
simple_calculator_test/calc.py
simple_calculator_test-1.0.dist-info/LICENSE
simple_calculator_test-1.0.dist-info/METADATA
simple_calculator_test-1.0.dist-info/WHEEL
simple_calculator_test-1.0.dist-info/top_level.txt
simple_calculator_test-1.0.dist-info/RECORD
