Metadata-Version: 2.1
Name: simple-calculator-test
Version: 1.0
Summary: Caculator for addition and subtraction
Home-page: UNKNOWN
Author: Author
Author-email: email@gmail.com
License: UNKNOWN
Platform: UNKNOWN
Classifier: Programming Language :: Python :: 3
Classifier: Operating System :: Microsoft :: Windows
Requires-Python: >=3.5
